cubicweb_blog/__init__.py
cubicweb_blog/__pkginfo__.py
cubicweb_blog/entities.py
cubicweb_blog/hooks.py
cubicweb_blog/schema.py
cubicweb_blog/site_cubicweb.py
cubicweb_blog/sobjects.py
cubicweb_blog/uiprops.py
cubicweb_blog/data/cubes.blog.css
cubicweb_blog/data/icon_blog.gif
cubicweb_blog/data/postdatabg.jpg
cubicweb_blog/i18n/en.po
cubicweb_blog/i18n/es.po
cubicweb_blog/i18n/fr.po
cubicweb_blog/migration/1.2.0_Any.py
cubicweb_blog/migration/1.4.2_Any.py
cubicweb_blog/migration/1.5.0_Any.py
cubicweb_blog/migration/1.7.0_Any.py
cubicweb_blog/migration/1.7.2_Any.py
cubicweb_blog/migration/1.7.3_Any.py
cubicweb_blog/migration/1.9.0_Any.py
cubicweb_blog/migration/postcreate.py
cubicweb_blog/views/__init__.py
cubicweb_blog/views/blog.py
cubicweb_blog/views/boxes.py
cubicweb_blog/views/entry.py
cubicweb_blog/views/urlpublishing.py
cubicweb_blog-3.1.1.dist-info/METADATA
cubicweb_blog-3.1.1.dist-info/WHEEL
cubicweb_blog-3.1.1.dist-info/entry_points.txt
cubicweb_blog-3.1.1.dist-info/top_level.txt
cubicweb_blog-3.1.1.dist-info/RECORD
